tgnet/__init__.py
tgnet/raw/__init__.py
tgnet/raw/auth.py
tgnet/raw/datacenter.py
tgnet/raw/headers.py
tgnet/raw/ip.py
tgnet/raw/salt.py
tgnet/raw/session.py
tgnet/raw/tgnet_reader.py
tgnet/tgnet.py
tgnet/utils.py
tgnet-0.2.1.dist-info/LICENSE
tgnet-0.2.1.dist-info/METADATA
tgnet-0.2.1.dist-info/WHEEL
tgnet-0.2.1.dist-info/RECORD
