Metadata-Version: 2.3
Name: tgnet
Version: 0.2.1
Summary: Deserializes/serializes Telegram tgnet.dat format. Can be used to extract/replace authKey and dcId.
Author: RuslanUC
Author-email: dev_ruslan_uc@protonmail.com
Requires-Python: >=3.10,<4.0
Classifier: Programming Language :: Python :: 3
Classifier: Programming Language :: Python :: 3.10
Classifier: Programming Language :: Python :: 3.11
Classifier: Programming Language :: Python :: 3.12
Classifier: Programming Language :: Python :: 3.13
